suki/__init__.py
suki/suki.py
suki-0.0.7.data/scripts/suki.py
suki-0.0.7.dist-info/LICENSE
suki-0.0.7.dist-info/METADATA
suki-0.0.7.dist-info/WHEEL
suki-0.0.7.dist-info/entry_points.txt
suki-0.0.7.dist-info/top_level.txt
suki-0.0.7.dist-info/RECORD
