Metadata-Version: 2.1
Name: suki
Version: 0.0.7
Summary: Suki is a Python symbolic link package manager created to make Python package management similar to node_modules.
Home-page: https://github.com/battleoverflow/suki
Author: battleoverflow
Classifier: Programming Language :: Python :: 3
Classifier: License :: OSI Approved :: BSD License
Classifier: Operating System :: OS Independent
Requires-Python: >=3.6
License-File: LICENSE
Requires-Dist: argparse
Requires-Dist: faye
